MANIFEST.in
README.md
requirements.txt
setup.cfg
setup.py
markovx/__init__.py
markovx/model.py
markovx.egg-info/PKG-INFO
markovx.egg-info/SOURCES.txt
markovx.egg-info/dependency_links.txt
markovx.egg-info/requires.txt
markovx.egg-info/top_level.txt